gig.py
gig-1.2.0.dist-info/LICENSE
gig-1.2.0.dist-info/METADATA
gig-1.2.0.dist-info/WHEEL
gig-1.2.0.dist-info/entry_points.txt
gig-1.2.0.dist-info/top_level.txt
gig-1.2.0.dist-info/RECORD
