Metadata-Version: 2.1
Name: gig
Version: 1.2.0
Summary: Generate .gitignore templates from the command line
Home-page: https://github.com/sloria/gig
Author: Steven Loria
Author-email: sloria1@gmail.com
License: MIT
Keywords: git,github,gitignore,command-line
Classifier: License :: OSI Approved :: MIT License
Classifier: Programming Language :: Python :: 3
Classifier: Programming Language :: Python :: 3 :: Only
Classifier: Programming Language :: Python :: 3.8
Classifier: Programming Language :: Python :: 3.9
Classifier: Programming Language :: Python :: 3.10
Classifier: Programming Language :: Python :: 3.11
Classifier: Programming Language :: Python :: 3.12
Requires-Python: >=3.8
License-File: LICENSE
Requires-Dist: docopt
Requires-Dist: requests
Provides-Extra: dev
Requires-Dist: gig[tests] ; extra == 'dev'
Requires-Dist: pre-commit ~=3.6 ; extra == 'dev'
Requires-Dist: tox ; extra == 'dev'
Provides-Extra: tests
Requires-Dist: pytest ; extra == 'tests'
Requires-Dist: scripttest ; extra == 'tests'
